YggSimLib/YggSimLib.py
YggSimLib/__init__.py
yggsimlib-0.97.dist-info/licenses/LICENSE
yggsimlib-0.97.dist-info/METADATA
yggsimlib-0.97.dist-info/WHEEL
yggsimlib-0.97.dist-info/top_level.txt
yggsimlib-0.97.dist-info/RECORD
