Metadata-Version: 2.4
Name: YggSimLib
Version: 0.97
Summary: A library for interfacing with the kspice API for the Yggdrasil project
Author: Håkon Enerstvedt
Requires-Python: >=3.12
License-File: LICENSE
Requires-Dist: tk==0.1.0
Requires-Dist: networkx==3.4.2
Dynamic: author
Dynamic: description
Dynamic: description-content-type
Dynamic: license-file
Dynamic: requires-dist
Dynamic: requires-python
Dynamic: summary
